mistlefoot/__init__.py
mistlefoot/_modidx.py
mistlefoot/core.py
mistlefoot-0.0.2.dist-info/licenses/LICENSE
mistlefoot-0.0.2.dist-info/METADATA
mistlefoot-0.0.2.dist-info/WHEEL
mistlefoot-0.0.2.dist-info/entry_points.txt
mistlefoot-0.0.2.dist-info/top_level.txt
mistlefoot-0.0.2.dist-info/RECORD
