Metadata-Version: 2.4
Name: mistlefoot
Version: 0.0.2
Summary: Extended markdown features for mistletoe, including subscript, superscript, highlighting, emojis, footnotes, task lists, and more.
Home-page: https://github.com/AnswerDotAI/mistlefoot
Author: Jeremy Howard
Author-email: github@jhoward.fastmail.fm
License: Apache-2.0
Keywords: nbdev jupyter notebook python
Classifier: Development Status :: 4 - Beta
Classifier: Intended Audience :: Developers
Classifier: Natural Language :: English
Classifier: Programming Language :: Python :: 3.10
Classifier: Programming Language :: Python :: 3.11
Classifier: Programming Language :: Python :: 3.12
Classifier: Programming Language :: Python :: 3.13
Requires-Python: >=3.10
License-File: LICENSE
Requires-Dist: fastcore
Requires-Dist: mistletoe
Provides-Extra: dev
Requires-Dist: ipython; extra == "dev"
Dynamic: author
Dynamic: author-email
Dynamic: classifier
Dynamic: description
Dynamic: description-content-type
Dynamic: home-page
Dynamic: keywords
Dynamic: license
Dynamic: license-file
Dynamic: provides-extra
Dynamic: requires-dist
Dynamic: requires-python
Dynamic: summary
